mercury_co_nz_api-1.0.5.dist-info/licenses/LICENSE
pymercury/__init__.py
pymercury/client.py
pymercury/config.py
pymercury/exceptions.py
pymercury/py.typed
pymercury/utils.py
pymercury/api/__init__.py
pymercury/api/client.py
pymercury/api/client_backup.py
pymercury/api/endpoints.py
pymercury/api/models/__init__.py
pymercury/api/models/account.py
pymercury/api/models/base.py
pymercury/api/models/billing.py
pymercury/api/models/broadband.py
pymercury/api/models/electricity.py
pymercury/api/models/gas.py
pymercury/oauth/__init__.py
pymercury/oauth/client.py
mercury_co_nz_api-1.0.5.dist-info/METADATA
mercury_co_nz_api-1.0.5.dist-info/WHEEL
mercury_co_nz_api-1.0.5.dist-info/top_level.txt
mercury_co_nz_api-1.0.5.dist-info/RECORD
