Metadata-Version: 2.4
Name: mercury-co-nz-api
Version: 1.0.5
Summary: Python library for Mercury.co.nz OAuth and API integration
Author-email: Bertrand Kintanar <bertrand.kintanar@gmail.com>
License-Expression: MIT
Project-URL: Homepage, https://github.com/bkintanar/pymercury
Project-URL: Documentation, https://github.com/bkintanar/pymercury#readme
Project-URL: Repository, https://github.com/bkintanar/pymercury.git
Project-URL: Issues, https://github.com/bkintanar/pymercury/issues
Keywords: mercury,energy,api,oauth,new-zealand,electricity,utilities
Classifier: Development Status :: 5 - Production/Stable
Classifier: Intended Audience :: Developers
Classifier: Operating System :: OS Independent
Classifier: Programming Language :: Python :: 3
Classifier: Programming Language :: Python :: 3.7
Classifier: Programming Language :: Python :: 3.8
Classifier: Programming Language :: Python :: 3.9
Classifier: Programming Language :: Python :: 3.10
Classifier: Programming Language :: Python :: 3.11
Classifier: Programming Language :: Python :: 3.12
Classifier: Topic :: Internet :: WWW/HTTP :: Dynamic Content
Classifier: Topic :: Software Development :: Libraries :: Python Modules
Classifier: Topic :: Utilities
Requires-Python: >=3.7
License-File: LICENSE
Requires-Dist: requests>=2.25.0
Provides-Extra: dev
Requires-Dist: python-dotenv>=0.19.0; extra == "dev"
Requires-Dist: pytest>=6.0; extra == "dev"
Requires-Dist: pytest-cov>=2.0; extra == "dev"
Requires-Dist: black>=21.0; extra == "dev"
Requires-Dist: flake8>=3.8; extra == "dev"
Requires-Dist: mypy>=0.800; extra == "dev"
Dynamic: license-file
